hush/__init__.py
hush/console.py
hush/keypairs.py
hush/passwords.py
hush/secrets.py
hush-2.0.0.dist-info/entry_points.txt
hush-2.0.0.dist-info/LICENSE
hush-2.0.0.dist-info/WHEEL
hush-2.0.0.dist-info/METADATA
hush-2.0.0.dist-info/RECORD
