Metadata-Version: 2.1
Name: hush
Version: 2.0.0
Summary: Minimalistic command line secret management
Home-page: https://github.com/lechgu/hush
License: BSD-3-Clause
Author: Lech Gudalewicz
Author-email: lechgu@gmail.com
Requires-Python: >=3.7,<3.10
Classifier: License :: OSI Approved :: BSD License
Classifier: Programming Language :: Python :: 3
Classifier: Programming Language :: Python :: 3.7
Classifier: Programming Language :: Python :: 3.8
Classifier: Programming Language :: Python :: 3.9
Requires-Dist: click (>=7.0,<8.0)
Requires-Dist: pycryptodome (>=3.9.4,<4.0.0)
Project-URL: Repository, https://github.com/lechgu/hush
